pontos/__init__.py
pontos/changelog/__init__.py
pontos/changelog/_parser.py
pontos/changelog/conventional_commits.py
pontos/changelog/errors.py
pontos/changelog/main.py
pontos/cpe/__init__.py
pontos/cpe/_cpe.py
pontos/enum.py
pontos/errors.py
pontos/git/__init__.py
pontos/git/_git.py
pontos/git/_status.py
pontos/github/__init__.py
pontos/github/_parser.py
pontos/github/actions/__init__.py
pontos/github/actions/_parser.py
pontos/github/actions/cmds.py
pontos/github/actions/core.py
pontos/github/actions/env.py
pontos/github/actions/errors.py
pontos/github/actions/event.py
pontos/github/actions/main.py
pontos/github/api/__init__.py
pontos/github/api/api.py
pontos/github/api/artifacts.py
pontos/github/api/billing.py
pontos/github/api/branch.py
pontos/github/api/client.py
pontos/github/api/code_scanning.py
pontos/github/api/contents.py
pontos/github/api/dependabot.py
pontos/github/api/errors.py
pontos/github/api/foo.json
pontos/github/api/helper.py
pontos/github/api/labels.py
pontos/github/api/organizations.py
pontos/github/api/packages.py
pontos/github/api/pull_requests.py
pontos/github/api/release.py
pontos/github/api/repositories.py
pontos/github/api/search.py
pontos/github/api/secret_scanning.py
pontos/github/api/tags.py
pontos/github/api/teams.py
pontos/github/api/users.py
pontos/github/api/workflows.py
pontos/github/cmds.py
pontos/github/main.py
pontos/github/models/__init__.py
pontos/github/models/artifact.py
pontos/github/models/base.py
pontos/github/models/billing.py
pontos/github/models/branch.py
pontos/github/models/code_scanning.py
pontos/github/models/dependabot.py
pontos/github/models/organization.py
pontos/github/models/packages.py
pontos/github/models/pull_request.py
pontos/github/models/release.py
pontos/github/models/search.py
pontos/github/models/secret_scanning.py
pontos/github/models/tag.py
pontos/github/models/user.py
pontos/github/models/workflow.py
pontos/github/pr_template.md
pontos/github/script/__init__.py
pontos/github/script/_parser.py
pontos-25.8.1.dist-info/LICENSE
pontos-25.8.1.dist-info/METADATA
pontos-25.8.1.dist-info/WHEEL
pontos-25.8.1.dist-info/entry_points.txt
pontos-25.8.1.dist-info/RECORD
