Metadata-Version: 2.3
Name: pontos
Version: 25.8.1
Summary: Common utilities and tools maintained by Greenbone Networks
License: GPL-3.0-or-later
Author: Greenbone AG
Author-email: info@greenbone.net
Requires-Python: >=3.9,<4.0
Classifier: Development Status :: 4 - Beta
Classifier: Environment :: Console
Classifier: Intended Audience :: Developers
Classifier: License :: OSI Approved :: GNU General Public License v3 or later (GPLv3+)
Classifier: Operating System :: OS Independent
Classifier: Programming Language :: Python :: 3
Classifier: Programming Language :: Python :: 3.9
Classifier: Programming Language :: Python :: 3.10
Classifier: Programming Language :: Python :: 3.11
Classifier: Programming Language :: Python :: 3.12
Classifier: Programming Language :: Python :: 3.13
Classifier: Topic :: Software Development :: Libraries :: Python Modules
Requires-Dist: colorful (>=0.5.4)
Requires-Dist: httpx[http2] (>=0.23)
Requires-Dist: lxml (>=4.9.0)
Requires-Dist: packaging (>=20.3)
Requires-Dist: python-dateutil (>=2.8.2)
Requires-Dist: rich (>=12.4.4)
Requires-Dist: semver (>=2.13)
Requires-Dist: shtab (>=1.7.0)
Requires-Dist: tomlkit (>=0.5.11)
Project-URL: Documentation, https://greenbone.github.io/pontos/
Project-URL: Homepage, https://github.com/greenbone/pontos/
Project-URL: Repository, https://github.com/greenbone/pontos/
